jio/__init__.py
jio/conversion.py
jio/docker.py
jio/exec.py
jio/io.py
jio/network.py
jio/scrape.py
jio-0.0.4.dist-info/DESCRIPTION.rst
jio-0.0.4.dist-info/METADATA
jio-0.0.4.dist-info/RECORD
jio-0.0.4.dist-info/WHEEL
jio-0.0.4.dist-info/metadata.json
jio-0.0.4.dist-info/top_level.txt
