Metadata-Version: 2.0
Name: jio
Version: 0.0.4
Summary: Jacobi's basic IO functions and helpers
Home-page: https://gitlab.com/__jacobi/jio
Author: Jacobi Petrucciani
Author-email: jacobi@mimirhq.com
License: MIT
Platform: UNKNOWN
